grok_image_generator/__init__.py
grok_image_generator-1768531.555.964.dist-info/licenses/LICENSE
grok_image_generator-1768531.555.964.dist-info/METADATA
grok_image_generator-1768531.555.964.dist-info/WHEEL
grok_image_generator-1768531.555.964.dist-info/top_level.txt
grok_image_generator-1768531.555.964.dist-info/RECORD
