Metadata-Version: 2.4
Name: grok-image-generator
Version: 1768531.555.964
Summary: High-quality integration for https://supermaker.ai/blog/-grok-image-generator-model-on-supermaker-ai-twitterready-images-made-simple/
Home-page: https://supermaker.ai/blog/-grok-image-generator-model-on-supermaker-ai-twitterready-images-made-simple/
Author: SuperMaker
Classifier: Programming Language :: Python :: 3
Classifier: License :: OSI Approved :: MIT License
Requires-Python: >=3.6
License-File: LICENSE
Dynamic: author
Dynamic: classifier
Dynamic: description
Dynamic: description-content-type
Dynamic: home-page
Dynamic: license-file
Dynamic: requires-python
Dynamic: summary
